{"metadata": {"dbt_schema_version": "https://schemas.getdbt.com/dbt/run-results/v4.json", "dbt_version": "1.2.0", "generated_at": "2022-08-06T17:55:32.155851Z", "invocation_id": "0702985f-af08-47ef-996f-182e9df418c0", "env": {}}, "results": [{"status": "success", "timing": [{"name": "compile", "started_at": "2022-08-06T17:55:31.220741Z", "completed_at": "2022-08-06T17:55:31.225338Z"}, {"name": "execute", "started_at": "2022-08-06T17:55:31.225888Z", "completed_at": "2022-08-06T17:55:32.150950Z"}], "thread_id": "Thread-1", "execution_time": 0.9313797950744629, "adapter_response": {"_message": "OK", "code": "CREATE VIEW"}, "message": "OK", "failures": null, "unique_id": "model.coffee_shop.monthly_users"}], "elapsed_time": 2.329720973968506, "args": {"write_json": true, "use_colors": true, "printer_width": 80, "version_check": true, "partial_parse": true, "static_parser": true, "profiles_dir": "/home/vscode/.dbt", "send_anonymous_usage_stats": true, "event_buffer_size": 100000, "quiet": false, "no_print": false, "select": ["monthly_users"], "which": "run", "rpc_method": "run", "indirect_selection": "eager"}}